{"filename":"D:\\Senior Spring\\Cloud Dev\\CS487-PA4\\function-app\\__azurite_db_blob_extent__.json","collections":[{"name":"$EXTENTS_COLLECTION$","data":[{"id":"a0593690-3cb6-4fd0-a23f-2bf00a548102","locationId":"Default","path":"a0593690-3cb6-4fd0-a23f-2bf00a548102","size":1181,"lastModifiedInMS":1777712440786,"meta":{"revision":4,"created":1777712440787,"version":0,"updated":1777712446965},"$loki":1,"LastModifyInMS":1777712446964}],"idIndex":[1],"binaryIndices":{"id":{"name":"id","dirty":false,"values":[0]}},"constraints":null,"uniqueNames":[],"transforms":{},"objType":"$EXTENTS_COLLECTION$","dirty":false,"cachedIndex":null,"cachedBinaryIndex":null,"cachedData":null,"adaptiveBinaryIndices":true,"transactional":false,"cloneObjects":false,"cloneMethod":"parse-stringify","asyncListeners":false,"disableMeta":false,"disableChangesApi":true,"disableDeltaChangesApi":true,"autoupdate":false,"serializableIndices":true,"disableFreeze":true,"ttl":null,"maxId":1,"DynamicViews":[],"events":{"insert":[],"update":[],"pre-insert":[],"pre-update":[],"close":[],"flushbuffer":[],"error":[],"delete":[null],"warning":[null]},"changes":[],"dirtyIds":[]}],"databaseVersion":1.5,"engineVersion":1.5,"autosave":true,"autosaveInterval":5000,"autosaveHandle":null,"throttledSaves":true,"options":{"persistenceMethod":"fs","autosave":true,"autosaveInterval":5000,"serializationMethod":"normal","destructureDelimiter":"$<\n"},"persistenceMethod":"fs","persistenceAdapter":null,"verbose":false,"events":{"init":[null],"loaded":[],"flushChanges":[],"close":[],"changes":[],"warning":[]},"ENV":"NODEJS"}